{
    "action": [
        {
            "action_type": "SET_VARIABLE", 
            "args_list": [
                {
                    "arg_type": 100030, 
                    "args_list": [
                        {
                            "__tuple__": true, 
                            "items": [
                                "STRING", 
                                "游戏状态"
                            ]
                        }
                    ], 
                    "sub_type": 1
                }, 
                {
                    "arg_type": 100003, 
                    "args_list": [
                        "初始化"
                    ], 
                    "sub_type": 1
                }
            ], 
            "bp": true, 
            "element_id": 1987403811000186, 
            "enable": true
        }, 
        {
            "action_type": "FOR_INT_DO_ACTION", 
            "args_list": [
                {
                    "arg_type": 100002, 
                    "args_list": [
                        {
                            "__tuple__": true, 
                            "items": [
                                "INTEGER", 
                                "Player ID", 
                                "local"
                            ]
                        }
                    ], 
                    "sub_type": 6
                }, 
                {
                    "arg_type": 100002, 
                    "args_list": [
                        1
                    ], 
                    "sub_type": 1
                }, 
                {
                    "arg_type": 100002, 
                    "args_list": [
                        4
                    ], 
                    "sub_type": 1
                }, 
                {
                    "arg_type": 100022, 
                    "args_list": [
                        {
                            "action_type": "IF_THEN_ELSE", 
                            "args_list": [
                                {
                                    "arg_type": 100021, 
                                    "args_list": [
                                        {
                                            "args_list": [
                                                {
                                                    "arg_type": 100025, 
                                                    "args_list": [
                                                        {
                                                            "__tuple__": true, 
                                                            "items": [
                                                                "PLAYER", 
                                                                "房主"
                                                            ]
                                                        }
                                                    ], 
                                                    "sub_type": "VARIABLE"
                                                }, 
                                                {
                                                    "arg_type": 100035, 
                                                    "args_list": [
                                                        "=="
                                                    ], 
                                                    "sub_type": 1
                                                }, 
                                                {
                                                    "arg_type": 100025, 
                                                    "args_list": [], 
                                                    "sub_type": "NONE_ROLE"
                                                }
                                            ], 
                                            "condition_type": "PLAYER_COMPARE", 
                                            "element_id": 1987403811130106, 
                                            "enable": true
                                        }
                                    ], 
                                    "sub_type": 1
                                }, 
                                {
                                    "arg_type": 100022, 
                                    "args_list": [
                                        {
                                            "action_type": "SET_VARIABLE", 
                                            "args_list": [
                                                {
                                                    "arg_type": 100030, 
                                                    "args_list": [
                                                        {
                                                            "__tuple__": true, 
                                                            "items": [
                                                                "PLAYER", 
                                                                "房主"
                                                            ]
                                                        }
                                                    ], 
                                                    "sub_type": 1
                                                }, 
                                                {
                                                    "arg_type": 100025, 
                                                    "args_list": [
                                                        {
                                                            "arg_type": 100002, 
                                                            "args_list": [
                                                                {
                                                                    "__tuple__": true, 
                                                                    "items": [
                                                                        "INTEGER", 
                                                                        "Player ID", 
                                                                        "local"
                                                                    ]
                                                                }
                                                            ], 
                                                            "sub_type": 6
                                                        }
                                                    ], 
                                                    "sub_type": "GET_ROLE_BY_INT"
                                                }
                                            ], 
                                            "bp": false, 
                                            "element_id": 1987403811130116, 
                                            "enable": true
                                        }
                                    ], 
                                    "sub_type": 1
                                }, 
                                {
                                    "arg_type": 100022, 
                                    "args_list": [], 
                                    "sub_type": 1
                                }
                            ], 
                            "bp": false, 
                            "element_id": 1987403811130092, 
                            "enable": true, 
                            "fake_op": []
                        }, 
                        {
                            "action_type": "IF_THEN_ELSE", 
                            "args_list": [
                                {
                                    "arg_type": 100021, 
                                    "args_list": [
                                        [
                                            14870405130034, 
                                            "判断玩家是否加入游戏", 
                                            1487040513, 
                                            "condition_type"
                                        ], 
                                        {
                                            "args_list": [
                                                {
                                                    "arg_type": 100025, 
                                                    "args_list": [
                                                        {
                                                            "arg_type": 100002, 
                                                            "args_list": [
                                                                {
                                                                    "__tuple__": true, 
                                                                    "items": [
                                                                        "INTEGER", 
                                                                        "Player ID", 
                                                                        "local"
                                                                    ]
                                                                }
                                                            ], 
                                                            "sub_type": 6
                                                        }
                                                    ], 
                                                    "sub_type": "GET_ROLE_BY_INT"
                                                }, 
                                                {
                                                    "arg_type": 100035, 
                                                    "args_list": [
                                                        "!="
                                                    ], 
                                                    "sub_type": 1
                                                }, 
                                                {
                                                    "arg_type": 100025, 
                                                    "args_list": [], 
                                                    "sub_type": "NONE_ROLE"
                                                }
                                            ], 
                                            "condition_type": "PLAYER_COMPARE", 
                                            "element_id": 14870405130046, 
                                            "enable": true
                                        }, 
                                        {
                                            "args_list": [
                                                {
                                                    "arg_type": 100180, 
                                                    "args_list": [
                                                        {
                                                            "arg_type": 100025, 
                                                            "args_list": [
                                                                {
                                                                    "arg_type": 100002, 
                                                                    "args_list": [
                                                                        {
                                                                            "__tuple__": true, 
                                                                            "items": [
                                                                                "INTEGER", 
                                                                                "Player ID", 
                                                                                "local"
                                                                            ]
                                                                        }
                                                                    ], 
                                                                    "sub_type": 6
                                                                }
                                                            ], 
                                                            "sub_type": "GET_ROLE_BY_INT"
                                                        }
                                                    ], 
                                                    "sub_type": "GET_ROLE_STATUS"
                                                }, 
                                                {
                                                    "arg_type": 100035, 
                                                    "args_list": [
                                                        "=="
                                                    ], 
                                                    "sub_type": 1
                                                }, 
                                                {
                                                    "arg_type": 100180, 
                                                    "args_list": [
                                                        1
                                                    ], 
                                                    "sub_type": 1
                                                }
                                            ], 
                                            "condition_type": "PLAYER_STATE_COMPARE", 
                                            "element_id": 14870405130003, 
                                            "enable": true
                                        }
                                    ], 
                                    "sub_type": 1
                                }, 
                                {
                                    "arg_type": 100022, 
                                    "args_list": [
                                        {
                                            "action_type": "SEND_CUSTOM_EVENT", 
                                            "args_list": [
                                                {
                                                    "arg_type": 100238, 
                                                    "args_list": [
                                                        1439767489
                                                    ], 
                                                    "sub_type": 1
                                                }, 
                                                {
                                                    "arg_type": 100002, 
                                                    "args_list": [
                                                        {
                                                            "__tuple__": true, 
                                                            "items": [
                                                                "INTEGER", 
                                                                "Player ID", 
                                                                "local"
                                                            ]
                                                        }
                                                    ], 
                                                    "sub_type": 6
                                                }
                                            ], 
                                            "bp": false, 
                                            "element_id": 1987403811000195, 
                                            "enable": true
                                        }
                                    ], 
                                    "sub_type": 1
                                }, 
                                {
                                    "arg_type": 100022, 
                                    "args_list": [], 
                                    "sub_type": 1
                                }
                            ], 
                            "bp": false, 
                            "element_id": 14870405130009, 
                            "enable": true, 
                            "fake_op": []
                        }
                    ], 
                    "sub_type": 1
                }
            ], 
            "bp": false, 
            "element_id": 14870405130023, 
            "enable": true
        }
    ], 
    "call_enabled": true, 
    "condition": [], 
    "enabled": true, 
    "event": [
        {
            "args_list": [], 
            "element_id": 1987403811000002, 
            "enable": true, 
            "event_type": "INIT_FINISHED"
        }
    ], 
    "group_id": "xXCyIQtuEe+MG7Buv8Jnm0", 
    "p_trigger_id": null, 
    "trigger_id": 1987403811, 
    "trigger_name": "游戏初始化", 
    "valid": true
}