{
    "local_variable": {
        "53215264": {
            "variable_dict": {
                "ABILITY": {
                    "skill": null
                }, 
                "UNIT_ENTITY": {
                    "hero": 0, 
                    "target": 0
                }
            }, 
            "variable_length_dict": {
                "hero": 0, 
                "skill": 0, 
                "target": 0
            }
        }, 
        "132288546": {
            "variable_dict": {
                "ABILITY": {
                    "skill": null
                }, 
                "BOOLEAN": {
                    "boolean": false, 
                    "is_shop_tips": false
                }, 
                "ITEM_ENTITY": {
                    "item": 0
                }, 
                "ITEM_NAME": {
                    "item_type": 0
                }, 
                "MODIFIER_ENTITY": {
                    "modifier": 0
                }, 
                "PLAYER": {
                    "player": 0
                }, 
                "STRING": {}
            }, 
            "variable_length_dict": {
                "boolean": 0, 
                "is_shop_tips": 0, 
                "item": 0, 
                "item_type": 0, 
                "modifier": 0, 
                "player": 0, 
                "skill": 0
            }
        }, 
        "257417285": {
            "variable_dict": {
                "MODIFIER_ENTITY": {
                    "magic_effect": 0
                }, 
                "UNIT_ENTITY": {
                    "target": 0
                }
            }, 
            "variable_length_dict": {
                "magic_effect": 0, 
                "target": 0
            }
        }, 
        "374857769": {
            "variable_dict": {
                "INTEGER": {
                    "goods_index": 0, 
                    "i": 0, 
                    "n": 0
                }, 
                "NEW_TIMER": {
                    "t": -1
                }, 
                "PLAYER": {
                    "player": 0
                }, 
                "UNIT_ENTITY": {
                    "store unit": 0, 
                    "unit": 0
                }
            }, 
            "variable_length_dict": {
                "goods_index": 0, 
                "i": 0, 
                "n": 0, 
                "player": 0, 
                "store unit": 0, 
                "t": 0, 
                "unit": 0
            }
        }, 
        "441966634": {
            "variable_dict": {
                "FLOAT": {
                    "pos": 0.0, 
                    "tips_size": 0.0
                }, 
                "PLAYER": {
                    "Player": 0
                }
            }, 
            "variable_length_dict": {
                "Player": 0, 
                "pos": 10, 
                "tips_size": 10
            }
        }, 
        "441966639": {
            "variable_dict": {
                "INTEGER": {
                    "Ci": 0, 
                    "Ri": 0, 
                    "i": 0, 
                    "index": 0
                }, 
                "PLAYER": {
                    "player": 0
                }, 
                "UNIT_GROUP": {
                    "unit group": []
                }
            }, 
            "variable_length_dict": {
                "Ci": 0, 
                "Ri": 0, 
                "i": 0, 
                "index": 0, 
                "player": 0, 
                "unit group": 0
            }
        }, 
        "472645660": {
            "variable_dict": {
                "ABILITY": {
                    "skill": null
                }, 
                "UNIT_ENTITY": {
                    "guard": 0, 
                    "hero": 0
                }
            }, 
            "variable_length_dict": {
                "guard": 0, 
                "hero": 0, 
                "skill": 0
            }
        }, 
        "492298298": {
            "variable_dict": {
                "ABILITY": {
                    "skill": null
                }, 
                "FLOAT": {
                    "total_damage": 0.0
                }, 
                "UNIT_ENTITY": {
                    "caster": 0, 
                    "target": 0
                }
            }, 
            "variable_length_dict": {
                "caster": 0, 
                "skill": 0, 
                "target": 0, 
                "total_damage": 0
            }
        }, 
        "503767069": {
            "variable_dict": {
                "ITEM_ENTITY": {}, 
                "PLAYER": {}
            }, 
            "variable_length_dict": {}
        }, 
        "509075511": {
            "variable_dict": {
                "ABILITY": {
                    "skill": null
                }, 
                "UNIT_ENTITY": {
                    "caster": 0, 
                    "guard": 0
                }
            }, 
            "variable_length_dict": {
                "caster": 0, 
                "guard": 0, 
                "skill": 0
            }
        }, 
        "525852710": {
            "variable_dict": {
                "INTEGER": {
                    "i": 0
                }, 
                "PLAYER": {
                    "player": 0
                }, 
                "UNIT_ENTITY": {
                    "store_unit": 0
                }
            }, 
            "variable_length_dict": {
                "i": 0, 
                "player": 0, 
                "store_unit": 0
            }
        }, 
        "534593552": {
            "variable_dict": {
                "INTEGER": {
                    "index": 0
                }, 
                "PLAYER": {
                    "player": 0
                }, 
                "UNIT_ENTITY": {
                    "unit": 0
                }
            }, 
            "variable_length_dict": {
                "index": 0, 
                "player": 0, 
                "unit": 0
            }
        }, 
        "539754517": {
            "variable_dict": {
                "ABILITY": {
                    "skill": null
                }, 
                "NEW_TIMER": {
                    "\u9c9c\u8840\u6253\u51fb": -1
                }, 
                "UNIT_ENTITY": {
                    "caster": 0, 
                    "target": 0
                }
            }, 
            "variable_length_dict": {
                "caster": 0, 
                "skill": 0, 
                "target": 0, 
                "\u9c9c\u8840\u6253\u51fb": 0
            }
        }, 
        "568463368": {
            "variable_dict": {
                "NEW_TIMER": {
                    "t": -1
                }, 
                "PLAYER": {
                    "player": 0
                }, 
                "UNIT_ENTITY": {
                    "unit": 0
                }
            }, 
            "variable_length_dict": {
                "player": 0, 
                "t": 0, 
                "unit": 0
            }
        }, 
        "570679369": {
            "variable_dict": {
                "INTEGER": {
                    "\u6218\u573aID": 0, 
                    "\u96be\u5ea6\u7d22\u5f15": 0
                }
            }, 
            "variable_length_dict": {
                "\u6218\u573aID": 0, 
                "\u96be\u5ea6\u7d22\u5f15": 0
            }
        }, 
        "657195028": {
            "variable_dict": {
                "UNIT_ENTITY": {
                    "hero": 0, 
                    "hero_guard": 0
                }
            }, 
            "variable_length_dict": {
                "hero": 0, 
                "hero_guard": 0
            }
        }, 
        "660070450": {
            "variable_dict": {
                "DYNAMIC_TRIGGER_INSTANCE": {
                    "t1": 0, 
                    "t2": 0
                }, 
                "ITEM_ENTITY": {
                    "item": 0
                }, 
                "PLAYER": {
                    "player": 0
                }
            }, 
            "variable_length_dict": {
                "item": 0, 
                "player": 0, 
                "t1": 0, 
                "t2": 0
            }
        }, 
        "671428624": {
            "variable_dict": {
                "DYNAMIC_TRIGGER_INSTANCE": {
                    "t1": 0, 
                    "t2": 0
                }, 
                "ITEM_ENTITY": {
                    "item": 0
                }, 
                "PLAYER": {
                    "player": 0
                }, 
                "UNIT_ENTITY": {
                    "unit": 0
                }
            }, 
            "variable_length_dict": {
                "item": 0, 
                "player": 0, 
                "t1": 0, 
                "t2": 0, 
                "unit": 0
            }
        }, 
        "676847677": {
            "variable_dict": {
                "ABILITY": {
                    "skill": null
                }, 
                "FLOAT": {
                    "chance": 0.0, 
                    "lost_HP": 0.0
                }, 
                "MOVER_ENTITY": {
                    "guard_charge_movement": 0, 
                    "guard_movement": 0
                }, 
                "PROJECTILE_ENTITY": {
                    "guard_charge": 0
                }, 
                "UNIT_ENTITY": {
                    "guard": 0, 
                    "hero": 0
                }
            }, 
            "variable_length_dict": {
                "chance": 0, 
                "guard": 0, 
                "guard_charge": 0, 
                "guard_charge_movement": 0, 
                "guard_movement": 0, 
                "hero": 0, 
                "lost_HP": 0, 
                "skill": 0
            }
        }, 
        "718082063": {
            "variable_dict": {
                "INTEGER": {
                    "index": 0, 
                    "n": 0
                }, 
                "PLAYER": {
                    "player": 0
                }, 
                "UNIT_ENTITY": {
                    "unit": 0
                }
            }, 
            "variable_length_dict": {
                "index": 0, 
                "n": 0, 
                "player": 0, 
                "unit": 0
            }
        }, 
        "741081106": {
            "variable_dict": {
                "ABILITY": {
                    "skill": null
                }, 
                "FLOAT": {
                    "range": 0.0
                }, 
                "UNIT_ENTITY": {
                    "hero": 0, 
                    "skill_target": 0
                }
            }, 
            "variable_length_dict": {
                "hero": 0, 
                "range": 0, 
                "skill": 0, 
                "skill_target": 0
            }
        }, 
        "743956536": {
            "variable_dict": {
                "UNIT_ENTITY": {
                    "hero": 0, 
                    "hero_guard": 0
                }
            }, 
            "variable_length_dict": {
                "hero": 0, 
                "hero_guard": 0
            }
        }, 
        "784007186": {
            "variable_dict": {
                "ABILITY": {
                    "skill": null
                }, 
                "FLOAT": {
                    "range": 0.0
                }, 
                "UNIT_ENTITY": {
                    "hero": 0, 
                    "skill_target": 0
                }
            }, 
            "variable_length_dict": {
                "hero": 0, 
                "range": 0, 
                "skill": 0, 
                "skill_target": 0
            }
        }, 
        "808189983": {
            "variable_dict": {
                "ABILITY": {
                    "skill": null
                }, 
                "UNIT_ENTITY": {
                    "hero": 0, 
                    "target": 0
                }
            }, 
            "variable_length_dict": {
                "hero": 0, 
                "skill": 0, 
                "target": 0
            }
        }, 
        "828813355": {
            "variable_dict": {
                "FLOAT": {
                    "time": 0.0
                }, 
                "NEW_TIMER": {
                    "t": -1
                }, 
                "PLAYER": {
                    "player": 0
                }, 
                "STRING": {
                    "info": ""
                }
            }, 
            "variable_length_dict": {
                "info": 0, 
                "player": 0, 
                "t": 0, 
                "time": 0
            }
        }, 
        "945283138": {
            "variable_dict": {
                "ABILITY": {
                    "skill": null
                }, 
                "UNIT_ENTITY": {
                    "hero": 0
                }
            }, 
            "variable_length_dict": {
                "hero": 0, 
                "skill": 0
            }
        }, 
        "993812551": {
            "variable_dict": {
                "INTEGER": {}, 
                "PLAYER": {
                    "Player": 0
                }, 
                "SCENE_UI": {}, 
                "TABLE": {
                    "\u8868": null
                }, 
                "TEXTURE": {
                    "\u56fe": 0
                }, 
                "UI_PREFAB_INSTANCE": {
                    "curUi": ""
                }
            }, 
            "variable_length_dict": {
                "Player": 0, 
                "curUi": 0, 
                "\u56fe": 0, 
                "\u8868": 0
            }
        }, 
        "1039151122": {
            "variable_dict": {
                "FLOAT": {
                    "pos": 0.0, 
                    "tips_size": 0.0
                }, 
                "PLAYER": {
                    "Player": 0
                }
            }, 
            "variable_length_dict": {
                "Player": 0, 
                "pos": 10, 
                "tips_size": 10
            }
        }, 
        "1113055299": {
            "variable_dict": {
                "ABILITY": {
                    "skill": null
                }, 
                "UNIT_ENTITY": {
                    "hero": 0, 
                    "target": 0
                }
            }, 
            "variable_length_dict": {
                "hero": 0, 
                "skill": 0, 
                "target": 0
            }
        }, 
        "1143734291": {
            "variable_dict": {
                "ABILITY": {
                    "skill": null
                }, 
                "UNIT_ENTITY": {
                    "caster": 0, 
                    "guard": 0
                }
            }, 
            "variable_length_dict": {
                "caster": 0, 
                "guard": 0, 
                "skill": 0
            }
        }, 
        "1146609709": {
            "variable_dict": {
                "INTEGER": {
                    "Ci": 0, 
                    "Ri": 0
                }, 
                "NEW_TIMER": {
                    "t": -1
                }, 
                "PLAYER": {
                    "player": 0
                }, 
                "UNIT_ENTITY": {
                    "unit": 0
                }
            }, 
            "variable_length_dict": {
                "Ci": 0, 
                "Ri": 0, 
                "player": 0, 
                "t": 0, 
                "unit": 0
            }
        }, 
        "1146609729": {
            "variable_dict": {
                "ABILITY": {
                    "skill": null
                }, 
                "UNIT_ENTITY": {
                    "hero": 0, 
                    "target": 0
                }
            }, 
            "variable_length_dict": {
                "hero": 0, 
                "skill": 0, 
                "target": 0
            }
        }, 
        "1159962657": {
            "variable_dict": {
                "MODIFIER_ENTITY": {
                    "magic_effect": 0
                }, 
                "UNIT_ENTITY": {
                    "target": 0
                }
            }, 
            "variable_length_dict": {
                "magic_effect": 0, 
                "target": 0
            }
        }, 
        "1163386924": {
            "variable_dict": {
                "INTEGER": {
                    "index": 0
                }, 
                "PLAYER": {
                    "player": 0
                }, 
                "UNIT_ENTITY": {
                    "unit": 0
                }
            }, 
            "variable_length_dict": {
                "index": 0, 
                "player": 0, 
                "unit": 0
            }
        }, 
        "1163386937": {
            "variable_dict": {
                "ABILITY": {
                    "skill": null
                }, 
                "NEW_TIMER": {
                    "\u9c9c\u8840\u6253\u51fb": -1
                }, 
                "UNIT_ENTITY": {
                    "caster": 0, 
                    "target": 0
                }
            }, 
            "variable_length_dict": {
                "caster": 0, 
                "skill": 0, 
                "target": 0, 
                "\u9c9c\u8840\u6253\u51fb": 0
            }
        }, 
        "1194065947": {
            "variable_dict": {
                "ABILITY": {
                    "skill": null
                }
            }, 
            "variable_length_dict": {
                "skill": 0
            }
        }, 
        "1325858865": {
            "variable_dict": {
                "INTEGER": {
                    "i": 0
                }, 
                "PLAYER": {
                    "player": 0
                }, 
                "UNIT_ENTITY": {
                    "store_unit": 0
                }
            }, 
            "variable_length_dict": {
                "i": 0, 
                "player": 0, 
                "store_unit": 0
            }
        }, 
        "1364713536": {
            "variable_dict": {
                "ABILITY": {
                    "skill": null
                }, 
                "UNIT_ENTITY": {
                    "guard": 0, 
                    "hero": 0
                }
            }, 
            "variable_length_dict": {
                "guard": 0, 
                "hero": 0, 
                "skill": 0
            }
        }, 
        "1381490734": {
            "variable_dict": {
                "NEW_TIMER": {
                    "t": -1
                }, 
                "PLAYER": {
                    "player": 0
                }, 
                "UNIT_ENTITY": {
                    "unit": 0
                }
            }, 
            "variable_length_dict": {
                "player": 0, 
                "t": 0, 
                "unit": 0
            }
        }, 
        "1393229841": {
            "variable_dict": {
                "DESTRUCTIBLE_ENTITY": {
                    "destructible": 0
                }, 
                "DYNAMIC_TRIGGER_INSTANCE": {
                    "t1": 0, 
                    "t2": 0
                }, 
                "ITEM_ENTITY": {
                    "item": 0
                }, 
                "PLAYER": {
                    "player": 0
                }, 
                "UNIT_ENTITY": {
                    "unit": 0
                }
            }, 
            "variable_length_dict": {
                "destructible": 0, 
                "item": 0, 
                "player": 0, 
                "t1": 0, 
                "t2": 0, 
                "unit": 0
            }
        }, 
        "1415045188": {
            "variable_dict": {
                "ABILITY": {
                    "skill": null
                }, 
                "UNIT_ENTITY": {
                    "hero": 0, 
                    "target": 0
                }
            }, 
            "variable_length_dict": {
                "hero": 0, 
                "skill": 0, 
                "target": 0
            }
        }, 
        "1425182768": {
            "variable_dict": {
                "INTEGER": {
                    "goods_index": 0, 
                    "n": 0, 
                    "new tab index": 0, 
                    "slot": 0
                }, 
                "NEW_TIMER": {
                    "t": -1
                }, 
                "PLAYER": {
                    "player": 0
                }, 
                "UNIT_ENTITY": {
                    "store unit": 0, 
                    "unit": 0
                }
            }, 
            "variable_length_dict": {
                "goods_index": 0, 
                "n": 0, 
                "new tab index": 0, 
                "player": 0, 
                "slot": 0, 
                "store unit": 0, 
                "t": 0, 
                "unit": 0
            }
        }, 
        "1559846928": {
            "variable_dict": {
                "INTEGER": {
                    "Ci": 0, 
                    "Ri": 0, 
                    "i": 0, 
                    "index": 0
                }, 
                "NEW_TIMER": {
                    "t": -1
                }, 
                "PLAYER": {
                    "player": 0
                }, 
                "UNIT_ENTITY": {
                    "unit": 0
                }, 
                "UNIT_GROUP": {
                    "unit group": []
                }
            }, 
            "variable_length_dict": {
                "Ci": 0, 
                "Ri": 0, 
                "i": 0, 
                "index": 0, 
                "player": 0, 
                "t": 0, 
                "unit": 0, 
                "unit group": 0
            }
        }, 
        "1582817317": {
            "variable_dict": {
                "INTEGER": {
                    "goods_index": 0, 
                    "n": 0, 
                    "new tab index": 0, 
                    "slot": 0
                }, 
                "PLAYER": {
                    "player": 0
                }
            }, 
            "variable_length_dict": {
                "goods_index": 0, 
                "n": 0, 
                "new tab index": 0, 
                "player": 0, 
                "slot": 0
            }
        }, 
        "1585119271": {
            "variable_dict": {
                "INTEGER": {
                    "goods_index": 0, 
                    "i": 0, 
                    "n": 0, 
                    "slot": 0
                }, 
                "NEW_TIMER": {
                    "t": -1
                }, 
                "PLAYER": {
                    "buyer player": 0, 
                    "player": 0
                }, 
                "UNIT_ENTITY": {
                    "store unit": 0, 
                    "unit": 0
                }
            }, 
            "variable_length_dict": {
                "buyer player": 0, 
                "goods_index": 0, 
                "i": 0, 
                "n": 0, 
                "player": 0, 
                "slot": 0, 
                "store unit": 0, 
                "t": 0, 
                "unit": 0
            }
        }, 
        "1649926197": {
            "variable_dict": {
                "ABILITY": {
                    "skill": null
                }, 
                "FLOAT": {
                    "range": 0.0
                }, 
                "UNIT_ENTITY": {
                    "hero": 0, 
                    "skill_target": 0
                }
            }, 
            "variable_length_dict": {
                "hero": 0, 
                "range": 0, 
                "skill": 0, 
                "skill_target": 0
            }
        }, 
        "1781268505": {
            "variable_dict": {
                "ABILITY": {
                    "skill": null
                }, 
                "FLOAT": {
                    "chance": 0.0, 
                    "lost_HP": 0.0
                }, 
                "MOVER_ENTITY": {
                    "guard_charge_movement": 0, 
                    "guard_movement": 0
                }, 
                "PROJECTILE_ENTITY": {
                    "guard_charge": 0
                }, 
                "UNIT_ENTITY": {
                    "guard": 0, 
                    "hero": 0
                }
            }, 
            "variable_length_dict": {
                "chance": 0, 
                "guard": 0, 
                "guard_charge": 0, 
                "guard_charge_movement": 0, 
                "guard_movement": 0, 
                "hero": 0, 
                "lost_HP": 0, 
                "skill": 0
            }
        }, 
        "1784143920": {
            "variable_dict": {
                "DESTRUCTIBLE_ENTITY": {
                    "destructible": 0
                }, 
                "DYNAMIC_TRIGGER_INSTANCE": {
                    "t1": 0, 
                    "t2": 0
                }, 
                "PLAYER": {
                    "player": 0
                }
            }, 
            "variable_length_dict": {
                "destructible": 0, 
                "player": 0, 
                "t1": 0, 
                "t2": 0
            }
        }, 
        "1872433179": {
            "variable_dict": {
                "ITEM_ENTITY": {}, 
                "PLAYER": {}
            }, 
            "variable_length_dict": {}
        }, 
        "1932263453": {
            "variable_dict": {
                "ABILITY": {
                    "skill": null
                }, 
                "UNIT_ENTITY": {
                    "hero": 0, 
                    "target": 0
                }
            }, 
            "variable_length_dict": {
                "hero": 0, 
                "skill": 0, 
                "target": 0
            }
        }, 
        "1935138870": {
            "variable_dict": {
                "ABILITY": {
                    "skill": null
                }, 
                "FLOAT": {
                    "range": 0.0
                }, 
                "UNIT_ENTITY": {
                    "hero": 0, 
                    "skill_target": 0
                }
            }, 
            "variable_length_dict": {
                "hero": 0, 
                "range": 0, 
                "skill": 0, 
                "skill_target": 0
            }
        }, 
        "1951916072": {
            "variable_dict": {
                "FLOAT": {
                    "time": 0.0
                }, 
                "NEW_TIMER": {
                    "t": -1
                }, 
                "PLAYER": {
                    "player": 0
                }, 
                "STRING": {
                    "info": ""
                }
            }, 
            "variable_length_dict": {
                "info": 0, 
                "player": 0, 
                "t": 0, 
                "time": 0
            }
        }, 
        "1965817886": {
            "variable_dict": {
                "ABILITY": {
                    "skill": null
                }, 
                "UNIT_ENTITY": {
                    "hero": 0
                }
            }, 
            "variable_length_dict": {
                "hero": 0, 
                "skill": 0
            }
        }, 
        "1968693291": {
            "variable_dict": {
                "INTEGER": {
                    "index": 0, 
                    "n": 0
                }, 
                "PLAYER": {
                    "player": 0
                }, 
                "UNIT_ENTITY": {
                    "unit": 0
                }
            }, 
            "variable_length_dict": {
                "index": 0, 
                "n": 0, 
                "player": 0, 
                "unit": 0
            }
        }, 
        "1975832648": {
            "variable_dict": {
                "BOOLEAN": {
                    "temnp": false
                }, 
                "INTEGER": {
                    "\u6218\u573aID": 0, 
                    "\u6218\u5f79\u8868KEY": 0, 
                    "\u96be\u5ea6\u7d22\u5f15": 0
                }, 
                "TABLE_SAVE": {}
            }, 
            "variable_length_dict": {
                "temnp": 10, 
                "\u6218\u573aID": 0, 
                "\u6218\u5f79\u8868KEY": 0, 
                "\u96be\u5ea6\u7d22\u5f15": 0
            }
        }, 
        "1987403811": {
            "variable_dict": {
                "INTEGER": {
                    "Player ID": 0
                }
            }, 
            "variable_length_dict": {
                "Player ID": 0
            }
        }, 
        "2016149526": {
            "variable_dict": {
                "ABILITY": {
                    "skill": null
                }, 
                "FLOAT": {
                    "total_damage": 0.0
                }, 
                "UNIT_ENTITY": {
                    "caster": 0, 
                    "target": 0
                }
            }, 
            "variable_length_dict": {
                "caster": 0, 
                "skill": 0, 
                "target": 0, 
                "total_damage": 0
            }
        }, 
        "2035802182": {
            "variable_dict": {
                "MODIFIER_ENTITY": {
                    "magic_effect": 0
                }, 
                "UNIT_ENTITY": {
                    "caster": 0, 
                    "target": 0
                }
            }, 
            "variable_length_dict": {
                "caster": 0, 
                "magic_effect": 0, 
                "target": 0
            }
        }, 
        "2052579367": {
            "variable_dict": {
                "ABILITY": {
                    "skill": null
                }, 
                "BOOLEAN": {
                    "boolean": false, 
                    "is_shop_tips": false
                }, 
                "ITEM_ENTITY": {
                    "item": 0
                }, 
                "ITEM_NAME": {
                    "item_type": 0
                }, 
                "MODIFIER_ENTITY": {
                    "modifier": 0
                }, 
                "PLAYER": {
                    "player": 0
                }
            }, 
            "variable_length_dict": {
                "boolean": 0, 
                "is_shop_tips": 0, 
                "item": 0, 
                "item_type": 0, 
                "modifier": 0, 
                "player": 0, 
                "skill": 0
            }
        }, 
        "2067943458": {
            "variable_dict": {
                "MODIFIER_ENTITY": {
                    "magic_effect": 0
                }, 
                "UNIT_ENTITY": {
                    "caster": 0, 
                    "target": 0
                }
            }, 
            "variable_length_dict": {
                "caster": 0, 
                "magic_effect": 0, 
                "target": 0
            }
        }, 
        "2079805465": {
            "variable_dict": {
                "INTEGER": {
                    "Ci": 0, 
                    "Ri": 0, 
                    "cindex": 0, 
                    "i": 0, 
                    "rindex": 0
                }, 
                "NEW_TIMER": {
                    "t": -1
                }, 
                "PLAYER": {
                    "player": 0
                }, 
                "UNIT_ENTITY": {
                    "unit": 0
                }
            }, 
            "variable_length_dict": {
                "Ci": 0, 
                "Ri": 0, 
                "cindex": 0, 
                "i": 0, 
                "player": 0, 
                "rindex": 0, 
                "t": 0, 
                "unit": 0
            }
        }, 
        "2119688255": {
            "variable_dict": {
                "ABILITY": {
                    "skill": null
                }
            }, 
            "variable_length_dict": {
                "skill": 0
            }
        }
    }, 
    "variable_dict": {
        "INTEGER": {
            "GLOBAL_BAG_MAX_NUM": 0
        }, 
        "PLAYER": {
            "\u623f\u4e3b": 0
        }, 
        "STRING": {
            "\u6e38\u620f\u72b6\u6001": "\u521d\u59cb\u5316"
        }, 
        "TABLE": {
            "UI_Manager": null
        }, 
        "UNIT_ENTITY": {
            "Player Unit": 0
        }, 
        "UNIT_NAME": {}
    }, 
    "variable_group_info": [
        {
            "__tuple__": true, 
            "items": [
                "UI_Manager", 
                "UI_Manager"
            ]
        }, 
        {
            "__tuple__": true, 
            "items": [
                "GLOBAL_BAG_MAX_NUM", 
                "GLOBAL_BAG_MAX_NUM"
            ]
        }, 
        {
            "__tuple__": true, 
            "items": [
                "Player Unit", 
                "Player Unit"
            ]
        }, 
        {
            "__tuple__": true, 
            "items": [
                "\u6e38\u620f\u72b6\u6001", 
                "\u6e38\u620f\u72b6\u6001"
            ]
        }, 
        {
            "__tuple__": true, 
            "items": [
                "\u623f\u4e3b", 
                "\u623f\u4e3b"
            ]
        }
    ], 
    "variable_length_dict": {
        "GLOBAL_BAG_MAX_NUM": 0, 
        "Player Unit": 10, 
        "UI_Manager": 0, 
        "\u623f\u4e3b": 0, 
        "\u6e38\u620f\u72b6\u6001": 0
    }
}